<annotation>
  <folder>image</folder>
  <filename>image_0_05_04.png</filename>
  <source>
    <database>Unknown</database>
    <annotation>Unknown</annotation>
    <image>Unknown</image>
  </source>
  <size>
    <width>2000</width>
    <height>2000</height>
    <depth>3</depth>
  </size>
  <segmented>0</segmented>
  <object>
    <name>Car</name>
    <bndbox>
      <xmin>774.240234375</xmin>
      <ymin>1844.435546875</ymin>
      <xmax>819.9651489257812</xmax>
      <ymax>1891.89595413208</ymax>
    </bndbox>
  </object>
  <object>
    <name>Car</name>
    <bndbox>
      <xmin>634.0</xmin>
      <ymin>1629.447265625</ymin>
      <xmax>684.3117980957031</xmax>
      <ymax>1679.4000000000015</ymax>
    </bndbox>
  </object>
  <object>
    <name>Car</name>
    <bndbox>
      <xmin>340.720703125</xmin>
      <ymin>1124.73828125</ymin>
      <xmax>389.2790756225586</xmax>
      <ymax>1181.7616081237793</ymax>
    </bndbox>
  </object>
</annotation>
